scatter_downsample/__init__.py
scatter_downsample/__main__.py
scatter_downsample/function.py
scatter_downsample/helpers.py
scatter_downsample-0.2.6.dist-info/LICENSE
scatter_downsample-0.2.6.dist-info/METADATA
scatter_downsample-0.2.6.dist-info/WHEEL
scatter_downsample-0.2.6.dist-info/entry_points.txt
scatter_downsample-0.2.6.dist-info/top_level.txt
scatter_downsample-0.2.6.dist-info/RECORD
