Metadata-Version: 2.1
Name: scatter-downsample
Version: 0.2.6
Summary: A module used for downsampling high resolution images using the scattering transform
Home-page: https://github.com/twardlab/ScatteringDownsample
Author: jaqueline_lu
Author-email: jellalu21@gmail.com
License: UNKNOWN
Platform: UNKNOWN
Classifier: Programming Language :: Python :: 3
Classifier: License :: OSI Approved :: Apache Software License
Classifier: Operating System :: OS Independent
Requires-Python: >=3.6
Requires-Dist: numpy
Requires-Dist: matplotlib
Requires-Dist: scipy
